class test
{
/* 2: var cnt:int :=0 */
	field static int cnt = 0
	method public static void main(java.lang.String[])
	max_stack 15
	max_locals 15
	{
/* 3: begin */
/* 4:     var i:int */
/* 5:     var j:int := 0 */
		sipush 0
		istore 1
/* 6:     for i : 1..10 */
sipush 1
istore 0
L0:
iload 0
sipush 10
isub
ifgt L1
/* 7:         for j: 1..10 */
sipush 1
istore 1
L2:
iload 1
sipush 10
isub
ifgt L3
		getstatic int test.cnt
		sipush 1
/* 8:             cnt := cnt+1 */
iadd
putstatic int test.cnt
iload 1
sipush 1
iadd
istore 1
goto L2
L3:
/* 9:         end for */
getstatic java.io.PrintStream java.lang.System.out
		ldc "after "
/* 10:         put ("after ") */
invokevirtual void java.io.PrintStream.print(java.lang.String)
getstatic java.io.PrintStream java.lang.System.out
/* 11:         put i */
		iload 0
invokevirtual void java.io.PrintStream.print(int)
getstatic java.io.PrintStream java.lang.System.out
		ldc " "
/* 12:         put (" ") */
invokevirtual void java.io.PrintStream.print(java.lang.String)
getstatic java.io.PrintStream java.lang.System.out
/* 13:         put cnt */
		getstatic int test.cnt
invokevirtual void java.io.PrintStream.print(int)
getstatic java.io.PrintStream java.lang.System.out
invokevirtual void java.io.PrintStream.println()
/* 14:         skip */
iload 0
sipush 1
iadd
istore 0
goto L0
L1:
/* 15:     end for */
/* 16: end */
/* 17:  */
getstatic java.io.PrintStream java.lang.System.out
		ldc "result :"
/* 18: put ("result :") */
invokevirtual void java.io.PrintStream.print(java.lang.String)
getstatic java.io.PrintStream java.lang.System.out
		getstatic int test.cnt
invokevirtual void java.io.PrintStream.print(int)
		return
	}
}